CODEval/About.py
CODEval/__init__.py
CODEval/main.py
codeval_benchmark-1.1.1.dist-info/METADATA
codeval_benchmark-1.1.1.dist-info/WHEEL
codeval_benchmark-1.1.1.dist-info/top_level.txt
codeval_benchmark-1.1.1.dist-info/RECORD
