Metadata-Version: 2.4
Name: CODEval-Benchmark
Version: 1.1.1
Summary: A Benchmark used to evaluate small large language models.
Requires-Dist: langchain
Requires-Dist: langchain-core
Requires-Dist: langchain-ollama
Requires-Dist: langchain-text-splitters
Requires-Dist: langsmith
Dynamic: description
Dynamic: description-content-type
Dynamic: requires-dist
Dynamic: summary
